crosslab/api_client/__init__.py
crosslab/api_client/client.py
crosslab/api_client/exceptions.py
crosslab/api_client/py.typed
crosslab/api_client/schemas.py
crosslab_api_client-0.0.1.dist-info/METADATA
crosslab_api_client-0.0.1.dist-info/WHEEL
crosslab_api_client-0.0.1.dist-info/top_level.txt
crosslab_api_client-0.0.1.dist-info/RECORD
