Metadata-Version: 2.1
Name: crosslab-api-client
Version: 0.0.1
Summary: The CrossLab API Client
Author: Johannes Nau
Author-email: johannes.nau@tu-ilmenau.de
Classifier: Programming Language :: Python :: 3
Classifier: License :: Other/Proprietary License
Classifier: Operating System :: OS Independent
Requires-Python: <3.12,>=3.8
Requires-Dist: aiohttp
Requires-Dist: python-dateutil
